smgo_model/__init__.py
smgo_model/models/__init__.py
smgo_model/models/entidad.py
vanda_smgo_model-1.1.2.dist-info/METADATA
vanda_smgo_model-1.1.2.dist-info/WHEEL
vanda_smgo_model-1.1.2.dist-info/top_level.txt
vanda_smgo_model-1.1.2.dist-info/RECORD
