Metadata-Version: 2.4
Name: vanda_smgo_model
Version: 1.1.2
Summary: Test de librería pip
Author-email: Vanda Dev <kevins.villatoro@vanda.cl>
Project-URL: Homepage, https://github.com/SmartGO-Inc/smartgo-model-libreria.git
Project-URL: Bug Tracker, https://github.com/SmartGO-Inc/smartgo-model-libreria/issues
Classifier: Programming Language :: Python :: 3
Classifier: License :: OSI Approved :: MIT License
Classifier: Operating System :: OS Independent
Requires-Python: >=3.7
